mcp_agent_connector/__init__.py
mcp_agent_connector/main.py
mcp_agent_connector-0.1.0.dist-info/METADATA
mcp_agent_connector-0.1.0.dist-info/WHEEL
mcp_agent_connector-0.1.0.dist-info/top_level.txt
mcp_agent_connector-0.1.0.dist-info/RECORD
